LICENSE
MANIFEST.in
README.rst
setup.py
umysqldb/__init__.py
umysqldb/connections.py
umysqldb/cursors.py
umysqldb/err.py
umysqldb/times.py
umysqldb/util.py
umysqldb.egg-info/PKG-INFO
umysqldb.egg-info/SOURCES.txt
umysqldb.egg-info/dependency_links.txt
umysqldb.egg-info/requires.txt
umysqldb.egg-info/top_level.txt