Metadata-Version: 1.1
Name: umysqldb
Version: 1.0.2
Summary: MySQLdb compatible wrapper for ultramysql
Home-page: https://github.com/hongqn/umysqldb
Author: Qiangning Hong
Author-email: hongqn@douban.com
License: BSD License
Platform: any
Classifier: Intended Audience :: Developers
Classifier: License :: OSI Approved :: BSD License
Classifier: Programming Language :: Python
Classifier: Topic :: Database
Classifier: Topic :: Software Development :: Libraries :: Python Modules
